zyb_db/__init__.py
zyb_db/zyb_db.py
zyb_db/proxy/__init__.py
zyb_db/proxy/base.py
zyb_db/proxy/errors.py
zyb_db/proxy/mongo.py
zyb_db/proxy/tinydb.py
zyb_db-0.2.5.dist-info/METADATA
zyb_db-0.2.5.dist-info/WHEEL
zyb_db-0.2.5.dist-info/top_level.txt
zyb_db-0.2.5.dist-info/RECORD
